ibmcloudant/__init__.py
ibmcloudant/cloudant_base_service.py
ibmcloudant/cloudant_v1.py
ibmcloudant/common.py
ibmcloudant/couchdb_session_authenticator.py
ibmcloudant/couchdb_session_get_authenticator_patch.py
ibmcloudant/couchdb_session_token_manager.py
ibmcloudant/version.py
ibmcloudant/features/__init__.py
ibmcloudant/features/changes_follower.py
ibmcloudant/features/pagination.py
ibmcloudant-0.11.1.dist-info/licenses/LICENSE
ibmcloudant-0.11.1.dist-info/WHEEL
ibmcloudant-0.11.1.dist-info/METADATA
ibmcloudant-0.11.1.dist-info/RECORD
