Metadata-Version: 2.4
Name: ibmcloudant
Version: 0.11.1
Summary: Python client library for IBM Cloudant
Keywords: ibmcloudant,Cloudant,IBM,database,client,SDK,official
Author-email: IBM <cldtsdks@us.ibm.com>
Requires-Python: >=3.10
Classifier: Programming Language :: Python
Classifier: Programming Language :: Python :: 3
Classifier: Programming Language :: Python :: 3.10
Classifier: Programming Language :: Python :: 3.11
Classifier: Programming Language :: Python :: 3.12
Classifier: Programming Language :: Python :: 3.13
Classifier: Programming Language :: Python :: 3.14
Classifier: Development Status :: 5 - Production/Stable
Classifier: Intended Audience :: Developers
Classifier: License :: OSI Approved :: Apache Software License
Classifier: Operating System :: OS Independent
Classifier: Topic :: Software Development :: Libraries :: Python Modules
Classifier: Topic :: Software Development :: Libraries :: Application Frameworks
License-File: LICENSE
Requires-Dist: ibm_cloud_sdk_core==3.24.2
Requires-Dist: requests>=2.32.4,<3.0.0
Requires-Dist: python_dateutil>=2.5.3,<3.0.0
Requires-Dist: PyJWT>=2.0.1,<3.0.0
Project-URL: Bug Tracker, https://github.com/IBM/cloudant-python-sdk/issues
Project-URL: Homepage, https://github.com/IBM/cloudant-python-sdk
